hyperglass/.gitignore
hyperglass/__init__.py
hyperglass/api/__init__.py
hyperglass/api/error_handlers.py
hyperglass/api/events.py
hyperglass/api/examples/devices.py
hyperglass/api/examples/devices.sh
hyperglass/api/examples/queries.py
hyperglass/api/examples/queries.sh
hyperglass/api/examples/query.py
hyperglass/api/examples/query.sh
hyperglass/api/fake_output.py
hyperglass/api/routes.py
hyperglass/api/tasks.py
hyperglass/cache/__init__.py
hyperglass/cache/aio.py
hyperglass/cache/base.py
hyperglass/cache/sync.py
hyperglass/cli/__init__.py
hyperglass/cli/commands.py
hyperglass/cli/echo.py
hyperglass/cli/exceptions.py
hyperglass/cli/formatting.py
hyperglass/cli/installer.py
hyperglass/cli/static.py
hyperglass/cli/util.py
hyperglass/compat/__init__.py
hyperglass/compat/_asyncio.py
hyperglass/compat/_sshtunnel.py
hyperglass/configuration/.gitignore
hyperglass/configuration/__init__.py
hyperglass/configuration/main.py
hyperglass/configuration/markdown.py
hyperglass/configuration/validation.py
hyperglass/console.py
hyperglass/constants.py
hyperglass/defaults.py
hyperglass/encode.py
hyperglass/examples/commands.yaml
hyperglass/examples/devices.yaml
hyperglass/examples/hyperglass.yaml
hyperglass/exceptions.py
hyperglass/execution/__init__.py
hyperglass/execution/drivers/__init__.py
hyperglass/execution/drivers/_common.py
hyperglass/execution/drivers/_construct.py
hyperglass/execution/drivers/agent.py
hyperglass/execution/drivers/ssh.py
hyperglass/execution/drivers/ssh_netmiko.py
hyperglass/execution/drivers/ssh_scrapli.py
hyperglass/execution/main.py
hyperglass/external/__init__.py
hyperglass/external/_base.py
hyperglass/external/bgptools.py
hyperglass/external/generic.py
hyperglass/external/msteams.py
hyperglass/external/ripestat.py
hyperglass/external/rpki.py
hyperglass/external/slack.py
hyperglass/external/webhooks.py
hyperglass/images/hyperglass-dark.svg
hyperglass/images/hyperglass-icon.svg
hyperglass/images/hyperglass-light.svg
hyperglass-1.0.4.dist-info/entry_points.txt
hyperglass-1.0.4.dist-info/LICENSE
hyperglass-1.0.4.dist-info/WHEEL
hyperglass-1.0.4.dist-info/METADATA
hyperglass-1.0.4.dist-info/RECORD
