Metadata-Version: 2.1
Name: hyperglass
Version: 1.0.4
Summary: hyperglass is the modern network looking glass that tries to make the internet better.
Home-page: https://hyperglass.dev
License: BSD-3-Clause-Clear
Keywords: looking glass,network automation,isp,bgp,routing
Author: Matt Love
Author-email: matt@hyperglass.dev
Requires-Python: >=3.6.1,<4.0
Classifier: Development Status :: 5 - Production/Stable
Classifier: Intended Audience :: Information Technology
Classifier: License :: Other/Proprietary License
Classifier: Operating System :: POSIX :: Linux
Classifier: Programming Language :: JavaScript
Classifier: Programming Language :: Python :: 3
Classifier: Programming Language :: Python :: 3.6
Classifier: Programming Language :: Python :: 3.7
Classifier: Programming Language :: Python :: 3.8
Classifier: Programming Language :: Python :: 3.9
Classifier: Topic :: Internet
Classifier: Topic :: System :: Networking
Requires-Dist: Pillow (>=7.2,<8.0)
Requires-Dist: PyJWT (>=2.0.1,<3.0.0)
Requires-Dist: PyYAML (>=5.4.1,<6.0.0)
Requires-Dist: aiofiles (>=0.6.0,<0.7.0)
Requires-Dist: aredis (>=1.1.8,<2.0.0)
Requires-Dist: click (>=7.1.2,<8.0.0)
Requires-Dist: cryptography (==3.0.0)
Requires-Dist: distro (>=1.5.0,<2.0.0)
Requires-Dist: fastapi (>=0.63.0,<0.64.0)
Requires-Dist: favicons (>=0.0.9,<0.0.10)
Requires-Dist: gunicorn (>=20.1.0,<21.0.0)
Requires-Dist: httpx (>=0.17.1,<0.18.0)
Requires-Dist: inquirer (>=2.6.3,<3.0.0)
Requires-Dist: loguru (>=0.5.3,<0.6.0)
Requires-Dist: netmiko (>=3.4.0,<4.0.0)
Requires-Dist: paramiko (>=2.7.2,<3.0.0)
Requires-Dist: psutil (>=5.7.2,<6.0.0)
Requires-Dist: py-cpuinfo (>=7.0.0,<8.0.0)
Requires-Dist: pydantic (>=1.8.1,<2.0.0)
Requires-Dist: redis (>=3.5.3,<4.0.0)
Requires-Dist: scrapli[asyncssh] (>=2021.1.30,<2022.0.0)
Requires-Dist: uvicorn[standard] (>=0.13.4,<0.14.0)
Requires-Dist: uvloop (>=0.14.0,<0.15.0)
Requires-Dist: xmltodict (>=0.12.0,<0.13.0)
Project-URL: Documentation, https://hyperglass.dev
Project-URL: Repository, https://github.com/thatmattlove/hyperglass
